{"assets/Android.png":["assets/Android.png"],"assets/CSS.png":["assets/CSS.png"],"assets/Dart.png":["assets/Dart.png"],"assets/Flutter.png":["assets/Flutter.png"],"assets/Html.png":["assets/Html.png"],"assets/JavaScript.png":["assets/JavaScript.png"],"assets/Python.png":["assets/Python.png"],"assets/Web.png":["assets/Web.png"],"assets/facebook.png":["assets/facebook.png"],"assets/github.png":["assets/github.png"],"assets/image.png":["assets/image.png"],"assets/instagram.png":["assets/instagram.png"],"assets/linkedin.png":["assets/linkedin.png"],"assets/one.png":["assets/one.png"],"assets/phone.png":["assets/phone.png"],"assets/telegram.png":["assets/telegram.png"],"assets/three.png":["assets/three.png"],"assets/two.png":["assets/two.png"],"assets/website.png":["assets/website.png"],"packages/cupertino_icons/assets/CupertinoIcons.ttf":["packages/cupertino_icons/assets/CupertinoIcons.ttf"]}